gitx/__init__.py
gitx/__main__.py
gitx/cli.py
gitx/config.py
gitx/main.py
gitx/helpers/__init__.py
gitx/helpers/cli.py
gitx/helpers/git.py
gitx/helpers/paths.py
gitx/helpers/update.py
gitx_cli-0.3.0.dist-info/METADATA
gitx_cli-0.3.0.dist-info/WHEEL
gitx_cli-0.3.0.dist-info/entry_points.txt
gitx_cli-0.3.0.dist-info/top_level.txt
gitx_cli-0.3.0.dist-info/RECORD
