Metadata-Version: 2.4
Name: gitx-cli
Version: 0.3.0
Summary: Git superset CLI with workspace support
Author-email: Parisius <parisius@parisius.dev>
License-Expression: MIT
Classifier: Environment :: Console
Classifier: Intended Audience :: Developers
Requires-Python: >=3.10
Requires-Dist: typer>=0.12.0
Requires-Dist: rich>=13.7.0
